{
  "usuarios": [
    {
      "id": "4cd4",
      "nome": "Jefferson",
      "renda": "10000",
      "orcamentoDiario": 323.3333333333333
    }
  ],
  "transacoes": [
    {
      "id": "e480",
      "nome": "Livro",
      "valor": 40,
      "tipo": "despesa",
      "categoria": "Estudos",
      "data": "2025-07-30",
      "userId": "4cd4"
    },
    {
      "id": "9dce",
      "nome": "PIX",
      "valor": 40,
      "tipo": "receita",
      "categoria": "Pagamentos",
      "data": "2025-07-30",
      "userId": "4cd4"
    },
    {
      "id": "d919",
      "nome": "Pirulito",
      "valor": 10,
      "tipo": "despesa",
      "categoria": "Alimentação",
      "data": "2025-07-29",
      "userId": "4cd4"
    }
  ]
}